{
    "created_time": "2024-05-13T09:24:03Z",
    "files": [
    ],
    "folders": [
        {
            "name": "010_计算机发展历程"
        },
        {
            "name": "020_计算机的分类与发展方向"
        },
        {
            "name": "030_计算机系统的组成"
        },
        {
            "name": "040_计算机工作过程"
        },
        {
            "name": "050_计算机软件系统"
        },
        {
            "name": "060_计算机编程语言"
        },
        {
            "name": "070_计算机系统的层次结构"
        },
        {
            "name": "080_冯诺依曼计算机"
        },
        {
            "name": "090_存储器"
        },
        {
            "name": "100_计算机性能指标"
        }
    ],
    "id": "2732",
    "modified_time": "2024-05-13T09:24:03Z",
    "signature": "10876349421445045299",
    "version": 3
}
